README.md
setup.py
anomaly_detection/__init__.py
anomaly_detection/base.py
anomaly_detection/detector.py
anomaly_detection/emulator.py
anomaly_detection/forecaster.py
anomaly_detection/tester.py
anomaly_detection_ts.egg-info/PKG-INFO
anomaly_detection_ts.egg-info/SOURCES.txt
anomaly_detection_ts.egg-info/dependency_links.txt
anomaly_detection_ts.egg-info/requires.txt
anomaly_detection_ts.egg-info/top_level.txt