Metadata-Version: 1.0
Name: anomaly-detection-ts
Version: 0.2.1
Summary: anomaly detection sdk
Home-page: UNKNOWN
Author: WeiJi Hsiao
Author-email: UNKNOWN
License: UNKNOWN
Platform: UNKNOWN
